CHANGELOG.md
LICENSE
MANIFEST.in
Makefile
README.md
setup.cfg
setup.py
tox.ini
wc_django_filemonitor.egg-info/PKG-INFO
wc_django_filemonitor.egg-info/SOURCES.txt
wc_django_filemonitor.egg-info/dependency_links.txt
wc_django_filemonitor.egg-info/requires.txt
wc_django_filemonitor.egg-info/top_level.txt
wcd_filemonitor/__init__.py
wcd_filemonitor/apps.py
wcd_filemonitor/conf.py
wcd_filemonitor/signals.py
wcd_filemonitor/contrib/__init__.py
wcd_filemonitor/contrib/translations/__init__.py
wcd_filemonitor/contrib/translations/apps.py
wcd_filemonitor/contrib/translations/resolver.py
wcd_filemonitor/services/__init__.py
wcd_filemonitor/services/monitor.py
wcd_filemonitor/services/registry.py